[
  {
    "id": "b8acd5e1007a50e63725fa271b856e6f",
    "filename": "Big_Data_Analytics_1638521602.pdf",
    "title": "Big Data Analytics - Overview",
    "authors": [
      "Big Data"
    ],
    "filepath": "documents/Big_Data_Analytics_1638521602.pdf",
    "upload_date": "2025-05-26T22:48:56.971732",
    "file_size": 1457922,
    "summary": "This document provides an overview of big data analytics, including the challenges of dealing with large amounts of unstructured data and the process of collecting, munging, and delivering data products useful to organizations. The CRISP-DM methodology is also discussed as a framework for organizing the work needed by an organization to deliver clear insights from big data.",
    "keywords": [
      "big data",
      "analytics",
      "data mining",
      "CRISP-DM",
      "data life cycle"
    ],
    "category": "Machine Learning/Deep Learning",
    "difficulty": "Intermediate",
    "content_preview": "Big Data Analytics - Overview \nThe volume of data that one has to deal has exploded to unimaginable levels in the past decade, \nand at the same time, the price of data storage has systematically reduced. Private companies and \nresearch institutions capture terabytes of data about their users’ interactions, business, social \nmedia, and also sensors from devices such as mobile phones and automobiles. The challenge of \nthis era is to make sense of this sea of data. This is where big data analytics ..."
  }
]
